llama_index/readers/solr/__init__.py
llama_index/readers/solr/base.py
llama_index_readers_solr-0.1.0.dist-info/METADATA
llama_index_readers_solr-0.1.0.dist-info/WHEEL
llama_index_readers_solr-0.1.0.dist-info/licenses/LICENSE
llama_index_readers_solr-0.1.0.dist-info/RECORD
