Metadata-Version: 2.4
Name: llama-index-readers-solr
Version: 0.1.0
Summary: llama-index readers solr integration
Author-email: Xiaoyu Ouyang <xouyang1@bloomberg.net>, Atharva Tendle <atendle@bloomberg.net>, Steven Butler <sbutler81@bloomberg.net>, Vikramjeet Das <vdas22@bloomberg.net>, Yong Zhuang <yzhuang52@bloomberg.net>
Maintainer-email: Xiaoyu Ouyang <xouyang1@bloomberg.net>, Atharva Tendle <atendle@bloomberg.net>, Steven Butler <sbutler81@bloomberg.net>, Vikramjeet Das <vdas22@bloomberg.net>, Yong Zhuang <yzhuang52@bloomberg.net>
License-Expression: MIT
License-File: LICENSE
Requires-Python: <4.0,>=3.9
Requires-Dist: llama-index-core<0.15,>=0.14.0
Requires-Dist: pysolr>=3.10.0
